kipa/__init__.py
kipa/kipa.py
kipa-0.0.9.dist-info/LICENSE
kipa-0.0.9.dist-info/METADATA
kipa-0.0.9.dist-info/WHEEL
kipa-0.0.9.dist-info/top_level.txt
kipa-0.0.9.dist-info/RECORD
