Metadata-Version: 2.1
Name: kipa
Version: 0.0.9
Summary: Convert Kurdish text to IPA phonetics
Home-page: https://github.com/kurd-cc/kipa
Author: Jagar Yousef
Author-email: <jagar.yousef@gmail.com>
License: UNKNOWN
Keywords: kurdish,language,language-processing,kurmanji,ipa,phonetics
Platform: UNKNOWN
Classifier: Development Status :: 1 - Planning
Classifier: Intended Audience :: Developers
Classifier: Programming Language :: Python :: 3
Classifier: Operating System :: Unix
Classifier: Operating System :: MacOS :: MacOS X
Classifier: Operating System :: Microsoft :: Windows
License-File: LICENSE
Requires-Dist: kwiki (>=0.0.8)
